Metadata-Version: 2.1
Name: xxx.scraper
Version: 0.94
Summary: scraper
Home-page: UNKNOWN
Author: 
Author-email: 
License: UNKNOWN
Keywords: web
Platform: UNKNOWN
Classifier: Programming Language :: Python
Classifier: Framework :: Pyramid
Classifier: Topic :: Internet :: WWW/HTTP
Classifier: Topic :: Internet :: WWW/HTTP :: WSGI :: Application
Provides-Extra: testing
